QSOLens/NetworkArchitecture.py
QSOLens/__init__.py
QSOLens/new_model_weights_3.h5
QSOLens-0.2.dist-info/LICENSE
QSOLens-0.2.dist-info/METADATA
QSOLens-0.2.dist-info/WHEEL
QSOLens-0.2.dist-info/entry_points.txt
QSOLens-0.2.dist-info/top_level.txt
QSOLens-0.2.dist-info/RECORD
