Metadata-Version: 2.1
Name: QSOLens
Version: 0.2
License-File: LICENSE
Requires-Dist: numpy
Requires-Dist: keras
